Metadata-Version: 2.1
Name: d5data-http-client
Version: 0.1.24
Summary: A simple HTTP client for the d5data API.
Home-page: https://github.com/d5data/d5data-http-client
Author: Tongzhou Jiang @ d5data.ai
Author-email: tojiang@d5data.ai
Classifier: Programming Language :: Python :: 3
Classifier: License :: OSI Approved :: MIT License
Classifier: Operating System :: OS Independent
Requires-Python: >=3.6
License-File: LICENSE
Requires-Dist: requests
